Workbook

Sheet Barcelona
A1: id | B1: name | C1: host_id | D1: host_profile_id | E1: host_name | F1: neighbourhood_group | G1: neighbourhood | H1: latitude | I1: longitude | J1: room_type | K1: price | L1: minimum_nights | M1: number_of_reviews | N1: last_review | O1: reviews_per_month | P1: calculated_host_listings_count | Q1: availability_365 | R1: number_of_reviews_ltm | S1: license
A2: 18674 | B2: Huge flat for 8 people close to Sagrada Familia | C2: 71615 | D2: 1.4625084e+18 | E2: Mireia | F2: Eixample | G2: la Sagrada FamÃ­lia | H2: 41.40556 | I2: 2.17262 | J2: Entire home/apt | L2: 1 | M2: 54 | N2: 45980 | O2: 0.35 | P2: 24 | Q2: 115 | R2: 9 | S2: Spain - National registration number<br />ESFCTU000008058000039706000000000000000HUTB-002062349<br /><br />Barcelona - Regional registration number<br />HUTB-002062
A3: 2031134 | B3: Sagrada Familia-auditorium. FREE WI-FI. | C3: 9100900 | D3: 1.4627949e+18 | E3: Miguel | F3: Eixample | G3: el Fort Pienc | H3: 41.40001 | I3: 2.18416 | J3: Entire home/apt | L3: 2 | M3: 453 | N3: 45993 | O3: 3.16 | P3: 1 | Q3: 294 | R3: 52 | S3: Barcelona - Regional registration number<br />HUTB-008524<br /><br />Spain - National registration number<br />ESFCTU00000807200012837600000000000000000HUTB-0085249
A4: 4415694 | B4: DEEP PURPLE - RAMBLES | C4: 12385333 | D4: 1.4628866e+18 | E4: Yolanda | F4: Sants-MontjuÃ¯c | G4: el Poble Sec | H4: 41.3723 | I4: 2.16441 | J4: Entire home/apt | L4: 3 | M4: 182 | N4: 45970 | O4: 1.39 | P4: 2 | Q4: 115 | R4: 11 | S4: Barcelona - Regional registration number<br />HUTB-006856
A5: 4415780 | B5: Double Room "Barcelona" | C5: 4990426 | D5: 1.4626702e+18 | E5: Judith | F5: GrÃ cia | G5: la Vila de GrÃ cia | H5: 41.40667 | I5: 2.16152 | J5: Private room | L5: 1 | M5: 5 | N5: 42662 | O5: 0.04 | P5: 1 | Q5: 0 | R5: 0
A6: 5064035 | B6: Lovely 2 BD with terrace and wifi | C6: 1744516 | D6: 1.4625773e+18 | E6: Silvia & LuÃ­s | F6: GrÃ cia | G6: la Vila de GrÃ cia | H6: 41.39996 | I6: 2.16339 | J6: Entire home/apt | L6: 3 | M6: 128 | N6: 45991 | O6: 0.99 | P6: 39 | Q6: 222 | R6: 23 | S6: Spain - National registration number<br />ESHFTU00000805700055108900800000000000000HUTB-0074460
A7: 5064651 | B7: Nice cute room for one person | C7: 26153633 | D7: 1.4653566e+18 | E7: Rabea | F7: Eixample | G7: la Sagrada FamÃ­lia | H7: 41.40687 | I7: 2.17813 | J7: Private room | L7: 1 | M7: 9 | N7: 43043 | O7: 0.07 | P7: 1 | Q7: 0 | R7: 0
A8: 6163177 | B8: Piso a 100 mts de la playa de BCN | C8: 31970000 | D8: 1.462657e+18 | E8: Pablo | F8: Sant MartÃ­ | G8: el Poblenou | H8: 41.39782 | I8: 2.20745 | J8: Private room | L8: 32 | M8: 14 | N8: 43324 | O8: 0.11 | P8: 1 | Q8: 365 | R8: 0
A9: 8414793 | B9: Lugaris Beach Premium Apartment | C9: 375625 | D9: 1.4625115e+18 | E9: Xavier | F9: Sant MartÃ­ | G9: el Poblenou | H9: 41.39909 | I9: 2.20733 | J9: Entire home/apt | L9: 1 | M9: 300 | N9: 45982 | O9: 2.47 | P9: 5 | Q9: 190 | R9: 96 | S9: Barcelona - Regional registration number<br />HUTB-002924
A10: 9357521 | B10: Three bedroom apartment Gran de Gracia You Stylish | C10: 8130906 | D10: 1.46275e+18 | E10: Eva | F10: GrÃ cia | G10: la Vila de GrÃ cia | H10: 41.39897 | I10: 2.15688 | J10: Entire home/apt | L10: 1 | M10: 160 | N10: 45972 | O10: 1.36 | P10: 64 | Q10: 325 | R10: 23 | S10: Barcelona - Regional registration number<br />HUTB-010949<br /><br />Spain - National registration number<br />ESFCTU00000806600038174900000000000000000HUTB-0109493
A11: 9358082 | B11: Bright, friendly and nice flat ! | C11: 48562201 | D11: 1.4657359e+18 | E11: Marie-GÃ©raldine | F11: Sant MartÃ­ | G11: el Clot | H11: 41.41029 | I11: 2.18694 | J11: Private room | L11: 1 | M11: 0 | P11: 1 | Q11: 0 | R11: 0
A12: 9362251 | B12: Plaza Espanya Apartime | C12: 4396136 | D12: 1.4626564e+18 | E12: Homesearch | F12: Sants-MontjuÃ¯c | G12: el Poble Sec | H12: 41.37333 | I12: 2.15451 | J12: Entire home/apt | L12: 3 | M12: 42 | N12: 45417 | O12: 0.36 | P12: 13 | Q12: 221 | R12: 0 | S12: Barcelona - Regional registration number<br />HUTB-005253
A13: 10031534 | B13: Cosy 1 BD APT with Balcony in Sagrada Familia | C13: 1744516 | D13: 1.4625773e+18 | E13: Silvia & LuÃ­s | F13: Eixample | G13: la Sagrada FamÃ­lia | H13: 41.40704 | I13: 2.18098 | J13: Entire home/apt | L13: 3 | M13: 58 | N13: 45972 | O13: 0.49 | P13: 39 | Q13: 296 | R13: 11 | S13: Spain - National registration number<br />ESFCTU000008073000928126000000000000000000HUTB0104059
A14: 10038461 | B14: Voyage Apart-Barcelona city centre | C14: 4687292 | D14: 1.4626633e+18 | E14: Gian | F14: Sants-MontjuÃ¯c | G14: el Poble Sec | H14: 41.37431 | I14: 2.16577 | J14: Entire home/apt | L14: 2 | M14: 464 | N14: 45984 | O14: 3.83 | P14: 1 | Q14: 251 | R14: 51 | S14: Spain - National registration number<br />ESFCTU00000806900001257600000000000000000HUTB-0027713<br /><br />Barcelona - Regional registration number<br />HUTB-002771
A15: 10078923 | B15: Barceloneta Street apartment | C15: 4116737 | D15: 1.4626478e+18 | E15: Elyess | F15: Ciutat Vella | G15: la Barceloneta | H15: 41.38223 | I15: 2.18798 | J15: Entire home/apt | L15: 31 | M15: 45 | N15: 45962 | O15: 0.38 | P15: 1 | Q15: 203 | R15: 5
A16: 11004309 | B16: Jardinets de GrÃ cia C, Barcelona! HUTB - 009099-92 | C16: 2688205 | D16: 1.4625257e+18 | E16: MÃ²nica | F16: GrÃ cia | G16: la Vila de GrÃ cia | H16: 41.39888 | I16: 2.16226 | J16: Entire home/apt | L16: 3 | M16: 396 | N16: 45992 | O16: 3.32 | P16: 13 | Q16: 226 | R16: 57 | S16: Barcelona - Regional registration number<br />HUTB-009099<br /><br />Spain - National registration number<br />ESFCTU00000805600026508800000000000000000HUTB-0126724
A17: 11008465 | B17: Sagrada Familia terrace flat | C17: 3744544 | D17: 1.4625316e+18 | E17: Marta+Paul | F17: Eixample | G17: la Sagrada FamÃ­lia | H17: 41.4055 | I17: 2.17727 | J17: Entire home/apt | L17: 3 | M17: 220 | N17: 45989 | O17: 1.9 | P17: 33 | Q17: 257 | R17: 35 | S17: Barcelona - Regional registration number<br />hutb-008493<br /><br />Spain - National registration number<br />ESFCTU00000807300025677900000000000000HUTB-008493-766
A18: 11547762 | B18: Big and central beautiful room | C18: 60951178 | D18: 1.4667505e+18 | E18: Yohanna | F18: Ciutat Vella | G18: la Barceloneta | H18: 41.38153 | I18: 2.18519 | J18: Private room | L18: 1 | M18: 2 | N18: 42529 | O18: 0.02 | P18: 1 | Q18: 0 | R18: 0
A19: 11550809 | B19: Excelente ubicaciÃ³n & fast Wifi | C19: 42613804 | D19: 1.4626911e+18 | E19: Vanina | F19: Eixample | G19: Sant Antoni | H19: 41.37554 | I19: 2.1649 | J19: Entire home/apt | L19: 32 | M19: 42 | N19: 45991 | O19: 0.36 | P19: 2 | Q19: 316 | R19: 2
A20: 11566581 | B20: Awesome double room in gotico area | C20: 12647360 | D20: 1.4628925e+18 | E20: Adam | F20: Ciutat Vella | G20: el Barri GÃ²tic | H20: 41.38183 | I20: 2.17637 | J20: Private room | L20: 3 | M20: 6 | N20: 42708 | O20: 0.05 | P20: 1 | Q20: 0 | R20: 0
A21: 11568230 | B21: B-Apartamento en casco antiguo. | C21: 22076771 | D21: 1.463171e+18 | E21: Luis | F21: Ciutat Vella | G21: el Barri GÃ²tic | H21: 41.38039 | I21: 2.17708 | J21: Entire home/apt | L21: 30 | M21: 15 | N21: 45897 | O21: 0.13 | P21: 20 | Q21: 246 | R21: 4 | S21: Spain - National registration number<br />ESFCNT00000811900021351700000000000000000000000000007
A22: 12355911 | B22: Room next to metro w/ own bathroom | C22: 143513 | D22: 1.46251e+18 | E22: Nabeelah | F22: Horta-GuinardÃ³ | G22: la Teixonera | H22: 41.42369 | I22: 2.14722 | J22: Private room | L22: 2 | M22: 40 | N22: 42910 | O22: 0.34 | P22: 1 | Q22: 0 | R22: 0
A23: 13093469 | B23: COZY DOUBLE ROOM IN PLAZA DE ESPAÃ‘A | C23: 16254397 | D23: 1.4629823e+18 | E23: Silvia | F23: Eixample | G23: Sant Antoni | H23: 41.37654 | I23: 2.1519 | J23: Private room | L23: 1 | M23: 0 | P23: 1 | Q23: 0 | R23: 0
A24: 13103577 | B24: Sunny Gothik and Port Apartment | C24: 2262273 | D24: 1.4625904e+18 | E24: Maria Rosa | F24: Ciutat Vella | G24: el Barri GÃ²tic | H24: 41.38149 | I24: 2.18035 | J24: Entire home/apt | L24: 32 | M24: 6 | N24: 44843 | O24: 0.07 | P24: 31 | Q24: 166 | R24: 0
A25: 13106697 | B25: La MediterrÃ¡nea - Homecelona Apts | C25: 2748428 | D25: 1.4625261e+18 | E25: Sha | F25: Sant MartÃ­ | G25: el Poblenou | H25: 41.395979 | I25: 2.2063944 | J25: Entire home/apt | L25: 4 | M25: 356 | N25: 45984 | O25: 3.08 | P25: 7 | Q25: 249 | R25: 39 | S25: Barcelona - Regional registration number<br />HUTB-009201<br /><br />Spain - National registration number<br />ESFCTU00000807200058235200000000000000HUTB-009201-366
A26: 13552869 | B26: Charming Private Room in City Centre. | C26: 16170032 | D26: 1.4629803e+18 | E26: Roberto | F26: Eixample | G26: Sant Antoni | H26: 41.37976 | I26: 2.1602 | J26: Private room | L26: 20 | M26: 3 | N26: 42595 | O26: 0.03 | P26: 1 | Q26: 0 | R26: 0
A27: 13844132 | B27: Nice Room in the Center of the city | C27: 81711867 | D27: 1.4669929e+18 | E27: Uxue | F27: Ciutat Vella | G27: el Raval | H27: 41.37752 | I27: 2.17272 | J27: Private room | L27: 3 | M27: 14 | N27: 42647 | O27: 0.12 | P27: 1 | Q27: 0 | R27: 0
A28: 14371490 | B28: Great Views, Near Beach, Port Vell | C28: 75620994 | D28: 1.4628158e+18 | E28: Sabrina | F28: Ciutat Vella | G28: el Barri GÃ²tic | H28: 41.38179 | I28: 2.18048 | J28: Entire home/apt | L28: 31 | M28: 14 | N28: 45869 | O28: 0.13 | P28: 13 | Q28: 365 | R28: 1 | S28: Spain - National registration number<br />ESFCNT00000811900011659700000000000000000000000000007
A29: 14378795 | B29: Downtown Barcelona! Ramblas, Plaza CataluÃ±a! | C29: 56503135 | D29: 1.4627347e+18 | E29: Flor | F29: Ciutat Vella | G29: el Barri GÃ²tic | H29: 41.38127 | I29: 2.17378 | J29: Private room | L29: 2 | M29: 325 | N29: 45613 | O29: 2.86 | P29: 2 | Q29: 0 | R29: 0
A30: 15293599 | B30: Big cozy aptm w/Central Heating by Las Ramblas! | C30: 55103645 | D30: 1.4659034e+18 | E30: David | F30: Ciutat Vella | G30: el Barri GÃ²tic | H30: 41.37959 | I30: 2.17627 | J30: Entire home/apt | L30: 32 | M30: 32 | N30: 45977 | O30: 0.29 | P30: 1 | Q30: 174 | R30: 7
A31: 15306390 | B31: Cozy Room at the City Center per long term rent | C31: 77548260 | D31: 1.4669505e+18 | E31: Andrea | F31: Eixample | G31: el Fort Pienc | H31: 41.39715 | I31: 2.17717 | J31: Private room | L31: 35 | M31: 16 | N31: 45809 | O31: 0.15 | P31: 8 | Q31: 105 | R31: 1 | S31: Spain - National registration number<br />ESHFNT00000805400056980900600000000000000000000000006
A32: 16266993 | B32: Acogedora habitaciÃ³n cerca de Sagrada Familia! | C32: 36607755 | D32: 1.4655452e+18 | E32: Room Housing | F32: Eixample | G32: la Sagrada FamÃ­lia | H32: 41.40302 | I32: 2.18124 | J32: Private room | L32: 32 | M32: 0 | P32: 136 | Q32: 365 | R32: 0
A33: 16270398 | B33: Nice dble bedroom to share next to the sea/center | C33: 106401998 | D33: 1.4672903e+18 | E33: Garnier | F33: Sant MartÃ­ | G33: el Poblenou | H33: 41.39752 | I33: 2.20144 | J33: Private room | L33: 3 | M33: 0 | P33: 1 | Q33: 0 | R33: 0
A34: 16278781 | B34: Kick Back on the Terrace of a Classic Home | C34: 8320838 | D34: 1.4627655e+18 | E34: Andrea And Jesse | F34: GrÃ cia | G34: la Vila de GrÃ cia | H34: 41.39759 | I34: 2.15418 | J34: Entire home/apt | L34: 2 | M34: 340 | N34: 45956 | O34: 3.12 | P34: 1 | Q34: 278 | R34: 30 | S34: Spain - National registration number<br />ESFCTU00000806600024844800000000000000000HUTB-0092304
A35: 16279645 | B35: Study in the center, in Gracia | C35: 94858265 | D35: 1.4671438e+18 | E35: Jose O | F35: GrÃ cia | G35: la Vila de GrÃ cia | H35: 41.39997 | I35: 2.1615 | J35: Entire home/apt | L35: 5 | M35: 245 | N35: 45971 | O35: 2.24 | P35: 4 | Q35: 140 | R35: 33 | S35: Spain - National registration number<br />ESFCTU000008057000241461000000000000000000HUTB0062672<br /><br />Barcelona - Regional registration number<br />HUTB-006267
A36: 16292600 | B36: BCN Luxury | C36: 15944590 | D36: 1.4629744e+18 | E36: Paco | F36: Eixample | G36: Sant Antoni | H36: 41.38521 | I36: 2.16299 | J36: Entire home/apt | L36: 4 | M36: 234 | N36: 45989 | O36: 2.15 | P36: 2 | Q36: 336 | R36: 31 | S36: Barcelona - Regional registration number<br />HUTB-013202
A37: 16294662 | B37: Double room in Villa de Gracia | C37: 106602227 | D37: 1.4672926e+18 | E37: Celia | F37: GrÃ cia | G37: la Vila de GrÃ cia | H37: 41.40071 | I37: 2.15473 | J37: Private room | L37: 1 | M37: 15 | N37: 43387 | O37: 0.14 | P37: 1 | Q37: 0 | R37: 0
A38: 16306389 | B38: Relaxing room in Sagrada Familia! | C38: 36607755 | D38: 1.4655452e+18 | E38: Room Housing | F38: Eixample | G38: la Sagrada FamÃ­lia | H38: 41.40496 | I38: 2.18148 | J38: Private room | L38: 32 | M38: 0 | P38: 136 | Q38: 364 | R38: 0
A39: 16306731 | B39: Beautiful & shinny room near to Sagrada Familia! | C39: 36607755 | D39: 1.4655452e+18 | E39: Room Housing | F39: Eixample | G39: la Sagrada FamÃ­lia | H39: 41.40458 | I39: 2.18123 | J39: Private room | L39: 32 | M39: 0 | P39: 136 | Q39: 364 | R39: 0
A40: 16306813 | B40: HabitaciÃ³n Soleada en Sagrada Familia! | C40: 36607755 | D40: 1.4655452e+18 | E40: Room Housing | F40: Eixample | G40: la Sagrada FamÃ­lia | H40: 41.4039 | I40: 2.17934 | J40: Private room | L40: 32 | M40: 0 | P40: 136 | Q40: 364 | R40: 0
A41: 16307165 | B41: CÃ³moda habitaciÃ³n en luminoso piso! | C41: 36607755 | D41: 1.4655452e+18 | E41: Room Housing | F41: Eixample | G41: la Sagrada FamÃ­lia | H41: 41.40325 | I41: 2.17972 | J41: Private room | L41: 32 | M41: 1 | N41: 44865 | O41: 0.03 | P41: 136 | Q41: 365 | R41: 0
A42: 16307967 | B42: Luminosa y moderna habitaciÃ³n con cama doble! | C42: 36607755 | D42: 1.4655452e+18 | E42: Room Housing | F42: Eixample | G42: la Sagrada FamÃ­lia | H42: 41.40521 | I42: 2.17974 | J42: Private room | L42: 32 | M42: 0 | P42: 136 | Q42: 364 | R42: 0
A43: 16308005 | B43: Comfortable & Beautiful Room! | C43: 36607755 | D43: 1.4655452e+18 | E43: Room Housing | F43: Eixample | G43: la Sagrada FamÃ­lia | H43: 41.40335 | I43: 2.17985 | J43: Private room | L43: 32 | M43: 0 | P43: 136 | Q43: 365 | R43: 0
A44: 16308030 | B44: Nice Room in Sagrada Familia | C44: 36607755 | D44: 1.4655452e+18 | E44: Room Housing | F44: Eixample | G44: la Sagrada FamÃ­lia | H44: 41.40351 | I44: 2.17971 | J44: Private room | L44: 32 | M44: 0 | P44: 136 | Q44: 365 | R44: 0
A45: 16308789 | B45: Amazing big room in Barcelona! | C45: 36607755 | D45: 1.4655452e+18 | E45: Room Housing | F45: Ciutat Vella | G45: el Barri GÃ²tic | H45: 41.38137 | I45: 2.17655 | J45: Private room | L45: 32 | M45: 0 | P45: 136 | Q45: 365 | R45: 0
A46: 16310328 | B46: Modern double bedroom in Barcelona! | C46: 36607755 | D46: 1.4655452e+18 | E46: Room Housing | F46: Ciutat Vella | G46: el Barri GÃ²tic | H46: 41.38167 | I46: 2.17634 | J46: Private room | L46: 32 | M46: 0 | P46: 136 | Q46: 365 | R46: 0
A47: 17491259 | B47: Elegant room in the heart of Barcelona | C47: 109295329 | D47: 1.4673232e+18 | E47: Sham | F47: Sants-MontjuÃ¯c | G47: el Poble Sec | H47: 41.37397 | I47: 2.155825 | J47: Private room | L47: 31 | M47: 135 | N47: 45290 | O47: 2.54 | P47: 2 | Q47: 270 | R47: 0
A48: 17512675 | B48: Luxurious Private Room in the Heart of Barcelona | C48: 107294697 | D48: 1.4673005e+18 | E48: Jess | F48: Eixample | G48: Sant Antoni | H48: 41.38293 | I48: 2.16163 | J48: Private room | L48: 1 | M48: 0 | P48: 4 | Q48: 0 | R48: 0
A49: 17513146 | B49: Stunning Room w/ Bathroom in Centre of Barcelona | C49: 107294697 | D49: 1.4673005e+18 | E49: Jess | F49: Eixample | G49: Sant Antoni | H49: 41.38364 | I49: 2.16186 | J49: Private room | L49: 1 | M49: 0 | P49: 4 | Q49: 0 | R49: 0
A50: 18028496 | B50: HabitaciÃ³n 2 +1 bien comunicado | C50: 124000696 | D50: 1.4682527e+18 | E50: Mar | F50: Horta-GuinardÃ³ | G50: el GuinardÃ³ | H50: 41.42231 | I50: 2.17855 | J50: Private room | L50: 1 | M50: 5 | N50: 42910 | O50: 0.05 | P50: 1 | Q50: 0 | R50: 0
A51: 18029085 | B51: 4-bedroom aptartment in Sant Antoni | C51: 10693680 | D51: 1.4628473e+18 | E51: RamÃ³n | F51: Eixample | G51: Sant Antoni | H51: 41.37992 | I51: 2.15876 | J51: Entire home/apt | L51: 32 | M51: 1 | N51: 44439 | O51: 0.02 | P51: 15 | Q51: 167 | R51: 0 | S51: Spain - National registration number<br />ESFCNT00000806900036839000000000000000000000000000001
A52: 18970396 | B52: Ð¡omfortable room | C52: 45120858 | D52: 1.4656697e+18 | E52: Alexei | F52: Nou Barris | G52: Verdun | H52: 41.44232 | I52: 2.17422 | J52: Private room | L52: 3 | M52: 0 | P52: 2 | Q52: 0 | R52: 0
A53: 18971689 | B53: Nice room | C53: 45120858 | D53: 1.4656697e+18 | E53: Alexei | F53: Nou Barris | G53: Verdun | H53: 41.44263 | I53: 2.17288 | J53: Private room | L53: 3 | M53: 0 | P53: 2 | Q53: 0 | R53: 0
A54: 18975870 | B54: Luminous Double w/Private bathroom Sagrada Familia | C54: 22685376 | D54: 1.4631858e+18 | E54: Robin | F54: Eixample | G54: la Sagrada FamÃ­lia | H54: 41.41024 | I54: 2.17401 | J54: Private room | L54: 10 | M54: 2 | N54: 42947 | O54: 0.02 | P54: 1 | Q54: 0 | R54: 0
A55: 18980901 | B55: "NEW"Double room + bathroom + private kitchenette | C55: 132312423 | D55: 1.4683234e+18 | E55: Carina | F55: Horta-GuinardÃ³ | G55: el GuinardÃ³ | H55: 41.41803 | I55: 2.17179 | J55: Private room | L55: 31 | M55: 191 | N55: 45988 | O55: 1.85 | P55: 1 | Q55: 79 | R55: 6 | S55: Spain - National registration number<br />ESHFNT00000805800015716500100000000000000000000000003
A56: 19011241 | B56: Les Corts | 2-Bedroom Apartment | C56: 129000409 | D56: 1.4629372e+18 | E56: Ittai | F56: Les Corts | G56: les Corts | H56: 41.384228 | I56: 2.136498 | J56: Entire home/apt | L56: 1 | M56: 149 | N56: 45949 | O56: 1.44 | P56: 15 | Q56: 347 | R56: 20 | S56: Barcelona - Regional registration number<br />HUTB-012438
A57: 19548275 | B57: Basic single room in the heart of Barcelona | C57: 137318065 | D57: 1.4683653e+18 | E57: Gabriela | F57: Eixample | G57: la Sagrada FamÃ­lia | H57: 41.40415 | I57: 2.17368 | J57: Private room | L57: 2 | M57: 79 | N57: 43443 | O57: 0.77 | P57: 2 | Q57: 0 | R57: 0
A58: 19840514 | B58: Amazing room in the heart of Barcelona | C58: 15512086 | D58: 1.4629641e+18 | E58: Oumaima | F58: Ciutat Vella | G58: el Raval | H58: 41.38146 | I58: 2.16796 | J58: Private room | L58: 3 | M58: 0 | P58: 1 | Q58: 0 | R58: 0
A59: 20281579 | B59: Private room close to Sagrada Familia | C59: 23736138 | D59: 1.4652779e+18 | E59: H. | F59: Eixample | G59: la Sagrada FamÃ­lia | H59: 41.40746 | I59: 2.17521 | J59: Private room | L59: 1 | M59: 22 | N59: 43058 | O59: 0.22 | P59: 1 | Q59: 0 | R59: 0
A60: 20291512 | B60: 1-4 Â· Sagrada Familia Views | C60: 58993125 | D60: 1.4667098e+18 | E60: Albert | F60: Eixample | G60: la Sagrada FamÃ­lia | H60: 41.405297 | I60: 2.1714082 | J60: Entire home/apt | L60: 1 | M60: 169 | N60: 45983 | O60: 1.67 | P60: 31 | Q60: 323 | R60: 32 | S60: Barcelona - Regional registration number<br />HUTB-011314
A61: 20298786 | B61: Sofia&Marina's hostel | C61: 144794990 | D61: 1.4684243e+18 | E61: Sofia | F61: Eixample | G61: la Sagrada FamÃ­lia | H61: 41.41082 | I61: 2.17672 | J61: Private room | L61: 1 | M61: 2 | N61: 42984 | O61: 0.02 | P61: 1 | Q61: 0 | R61: 0
A62: 21366324 | B62: HabitaciÃ³n privada en piso cÃ³modo a 15â€™ del centro | C62: 6499657 | D62: 1.462708e+18 | E62: Fernando | F62: Sant MartÃ­ | G62: el Clot | H62: 41.41488 | I62: 2.19182 | J62: Private room | L62: 2 | M62: 32 | N62: 43332 | O62: 0.32 | P62: 1 | Q62: 0 | R62: 0
A63: 21373867 | B63: HabitaciÃ³n tranquila en el barrio de Sants | C63: 57776439 | D63: 1.4627382e+18 | E63: Angel | F63: Sants-MontjuÃ¯c | G63: Sants | H63: 41.37635 | I63: 2.13369 | J63: Private room | L63: 31 | M63: 12 | N63: 45609 | O63: 0.42 | P63: 1 | Q63: 87 | R63: 0
A64: 21378611 | B64: Spacious apartment in the heart of Barcelona | C64: 154774388 | D64: 1.4685142e+18 | E64: FÃ¡tima | F64: Ciutat Vella | G64: el Barri GÃ²tic | H64: 41.38095 | I64: 2.17938 | J64: Entire home/apt | L64: 3 | M64: 290 | N64: 46000 | O64: 2.97 | P64: 1 | Q64: 222 | R64: 49 | S64: Spain - National registration number<br />ESFCTU0000081190001303330000000000000000HUBT000729740
A65: 21658683 | B65: Apartment Loft en La Rambla - BoquerÃ­a | C65: 117888638 | D65: 1.4682055e+18 | E65: Agustin | F65: Ciutat Vella | G65: el Barri GÃ²tic | H65: 41.38269 | I65: 2.17208 | J65: Entire home/apt | L65: 2 | M65: 4 | N65: 45219 | O65: 0.09 | P65: 6 | Q65: 285 | R65: 0 | S65: Spain - National registration number<br />ESHFTU00000805400049516000700000000000000HUTB-0358756<br /><br />Barcelona - Regional registration number<br />HUTB-035875
A66: 23030695 | B66: Working Room | C66: 170895136 | D66: 1.4686609e+18 | E66: Frank | F66: Sants-MontjuÃ¯c | G66: el Poble Sec | H66: 41.37313 | I66: 2.16854 | J66: Private room | L66: 31 | M66: 26 | N66: 45963 | O66: 0.34 | P66: 2 | Q66: 251 | R66: 4
A67: 23031576 | B67: Best location Gracia ***! | C67: 169257198 | D67: 1.4686369e+18 | E67: Marite | F67: GrÃ cia | G67: la Vila de GrÃ cia | H67: 41.39979 | I67: 2.16024 | J67: Entire home/apt | L67: 2 | M67: 349 | N67: 46004 | O67: 3.69 | P67: 1 | Q67: 224 | R67: 51 | S67: Spain - National registration number<br />ESFCTU00000806600016808100000000000000000000000045357
A68: 23500405 | B68: Habitacio â›ª la catedral | C68: 130179961 | D68: 1.4683048e+18 | E68: Juan Manuel | F68: Ciutat Vella | G68: el Barri GÃ²tic | H68: 41.38632 | I68: 2.17439 | J68: Private room | L68: 10 | M68: 0 | P68: 1 | Q68: 0 | R68: 0
A69: 23504187 | B69: Bright 2 bedroom apt in the heart of Barcelona | C69: 33427552 | D69: 1.4654892e+18 | E69: MarÃ­a Mercedes | F69: Ciutat Vella | G69: el Raval | H69: 41.38036 | I69: 2.16793 | J69: Private room | L69: 32 | M69: 1 | N69: 43198 | O69: 0.01 | P69: 1 | Q69: 87 | R69: 0
A70: 23992269 | B70: Lovely apartment near the center | C70: 35887104 | D70: 1.4655319e+18 | E70: Pilar | F70: Sants-MontjuÃ¯c | G70: el Poble Sec | H70: 41.3718 | I70: 2.16819 | J70: Entire home/apt | L70: 2 | M70: 208 | N70: 45999 | O70: 2.28 | P70: 1 | Q70: 254 | R70: 63 | S70: Spain - National registration number<br />ESFCTU00000806900099373800000000000000000HUTB-0112042
A71: 24010679 | B71: After october is entire flat with 3 bedroom 2 bath | C71: 15535606 | D71: 1.4629647e+18 | E71: Montse Jota | F71: Eixample | G71: Sant Antoni | H71: 41.375904 | I71: 2.1557889 | J71: Entire home/apt | L71: 32 | M71: 268 | N71: 45957 | O71: 2.86 | P71: 1 | Q71: 106 | R71: 32 | S71: Spain - National registration number<br />ESFCNT00000806900036094300000000000000000000000000007
A72: 24025489 | B72: Cool Jazz 41 - Habitat Apartments | C72: 158023606 | D72: 1.46854e+18 | E72: Habitat Apartments | F72: Horta-GuinardÃ³ | G72: el GuinardÃ³ | H72: 41.41275 | I72: 2.17632 | J72: Entire home/apt | L72: 1 | M72: 150 | N72: 45986 | O72: 1.61 | P72: 120 | Q72: 331 | R72: 36 | S72: Barcelona - Regional registration number<br />HUTB-011223<br /><br />Spain - National registration number<br />ESHFTU00000805800000659300300000000000000HUTB-0112231
A73: 24027579 | B73: Room in penthouse in diagonal, recently moved | C73: 60057552 | D73: 1.4667352e+18 | E73: Alex | F73: Les Corts | G73: les Corts | H73: 41.38623 | I73: 2.12791 | J73: Private room | L73: 30 | M73: 5 | N73: 43254 | O73: 0.05 | P73: 1 | Q73: 0 | R73: 0
A74: 24033028 | B74: "PLAZA DE TOROS" VINTAGE APARTAMENT | C74: 28300778 | D74: 1.4654178e+18 | E74: Mariana | F74: Eixample | G74: el Fort Pienc | H74: 41.39856 | I74: 2.18287 | J74: Entire home/apt | L74: 2 | M74: 480 | N74: 45984 | O74: 5.12 | P74: 1 | Q74: 295 | R74: 74 | S74: Barcelona - Regional registration number<br />HUTB-010021<br /><br />Spain - National registration number<br />ESFCTU00000807200037216800000000000000HUTB-010021-438
A75: 24465403 | B75: Nice apartment in central location. Monthly rental | C75: 172462374 | D75: 1.468674e+18 | E75: Apartaments UniÃ³ | F75: Ciutat Vella | G75: el Raval | H75: 41.37952 | I75: 2.17331 | J75: Entire home/apt | L75: 31 | M75: 27 | N75: 45942 | O75: 0.33 | P75: 15 | Q75: 110 | R75: 2
A76: 24465422 | B76: Full equipped! Two bedroom apartment, monthly rent | C76: 172462374 | D76: 1.468674e+18 | E76: Apartaments UniÃ³ | F76: Ciutat Vella | G76: el Raval | H76: 41.37959 | I76: 2.16836 | J76: Entire home/apt | L76: 31 | M76: 20 | N76: 45915 | O76: 0.24 | P76: 15 | Q76: 117 | R76: 3
A77: 26025302 | B77: Triple room, private bathroom near Sagrada Familia | C77: 195335908 | D77: 1.4631092e+18 | E77: Carlos | F77: Eixample | G77: la Sagrada FamÃ­lia | H77: 41.40059 | I77: 2.17547 | J77: Private room | L77: 1 | M77: 188 | N77: 46002 | O77: 2.21 | P77: 3 | Q77: 334 | R77: 21 | S77: Barcelona - Regional registration number<br />HUTB-004464<br /><br />Spain - National registration number<br />Exempt
A78: 26028659 | B78: BIG ROOM IN AWESOME LOCATION!! | C78: 148546410 | D78: 1.4684545e+18 | E78: Maria | F78: GrÃ cia | G78: la Vila de GrÃ cia | H78: 41.40055 | I78: 2.1543 | J78: Private room | L78: 7 | M78: 1 | N78: 43326 | O78: 0.01 | P78: 2 | Q78: 0 | R78: 0
A79: 26030039 | B79: Double room Ramblas Barcelona ( 31 days minium ) | C79: 160690738 | D79: 1.4630089e+18 | E79: Juan Jose | F79: Ciutat Vella | G79: el Raval | H79: 41.38294 | I79: 2.16909 | J79: Private room | L79: 31 | M79: 140 | N79: 45901 | O79: 1.55 | P79: 4 | Q79: 159 | R79: 5
A80: 26030842 | B80: Double Room Ramblas Barcelona ( 31 days minium ) | C80: 160690738 | D80: 1.4630089e+18 | E80: Juan Jose | F80: Ciutat Vella | G80: el Raval | H80: 41.38294 | I80: 2.16909 | J80: Private room | L80: 31 | M80: 121 | N80: 45874 | O80: 1.33 | P80: 4 | Q80: 363 | R80: 2
A81: 26043915 | B81: Apartment M.Claret | C81: 23213732 | D81: 1.4652702e+18 | E81: Silvia & Josep Lluis | F81: Eixample | G81: la Sagrada FamÃ­lia | H81: 41.41082 | I81: 2.17384 | J81: Entire home/apt | L81: 2 | M81: 191 | N81: 45971 | O81: 2.12 | P81: 4 | Q81: 246 | R81: 41 | S81: Barcelona - Regional registration number<br />HUTB-002183<br /><br />Spain - National registration number<br />ESFCTU00000805800025326300000000000000000000000000002
A82: 26096939 | B82: Bright and Open Apartment in Barcelona | C82: 26435442 | D82: 1.4653668e+18 | E82: Iris | F82: Les Corts | G82: les Corts | H82: 41.385 | I82: 2.13504 | J82: Private room | L82: 4 | M82: 2 | N82: 43688 | O82: 0.03 | P82: 1 | Q82: 0 | R82: 0
A83: 27644081 | B83: Superior Two bedroom apartment 32 | C83: 208199613 | D83: 1.4690861e+18 | E83: Coti Y Max | F83: Ciutat Vella | G83: el Barri GÃ²tic | H83: 41.38008 | I83: 2.17488 | J83: Entire home/apt | L83: 1 | M83: 132 | N83: 45952 | O83: 1.5 | P83: 15 | Q83: 155 | R83: 4 | S83: Barcelona - Regional registration number<br />HUTB-245289<br /><br />Spain - National registration number<br />ESHFTU00000805600071447000200000000000000HUTB-0024526
A84: 27644098 | B84: Superior Two bedroom apartment 12 | C84: 208199613 | D84: 1.4690861e+18 | E84: Coti Y Max | F84: Ciutat Vella | G84: el Raval | H84: 41.38019 | I84: 2.17327 | J84: Entire home/apt | L84: 1 | M84: 105 | N84: 45972 | O84: 1.19 | P84: 15 | Q84: 158 | R84: 9 | S84: Barcelona - Regional registration number<br />HUTB-245491<br /><br />Spain - National registration number<br />ESHFTU00000805600071447000400000000000000HUTB-0024548
A85: 27644115 | B85: One bedroom apartment | C85: 208199613 | D85: 1.4690861e+18 | E85: Coti Y Max | F85: Ciutat Vella | G85: el Raval | H85: 41.37825 | I85: 2.17473 | J85: Entire home/apt | L85: 1 | M85: 33 | N85: 45989 | O85: 0.39 | P85: 15 | Q85: 167 | R85: 7 | S85: Barcelona - Regional registration number<br />HUTB-245512<br /><br />Spain - National registration number<br />ESHFTU00000805600071447000500000000000000HUTB-0024554
A86: 27644158 | B86: Superior Two bedroom apartment | C86: 208199613 | D86: 1.4690861e+18 | E86: Coti Y Max | F86: Ciutat Vella | G86: el Raval | H86: 41.38012 | I86: 2.17353 | J86: Entire home/apt | L86: 1 | M86: 112 | N86: 45935 | O86: 1.3 | P86: 15 | Q86: 164 | R86: 6 | S86: Barcelona - Regional registration number<br />HUTB-245693<br /><br />Spain - National registration number<br />ESHFTU00000805600071447000600000000000000HUTB-0024560
A87: 29980781 | B87: Cozy, Romantic Apartment in Trendy Old World GrÃ ci | C87: 222058736 | D87: 1.469175e+18 | E87: Sara | F87: GrÃ cia | G87: la Vila de GrÃ cia | H87: 41.40222 | I87: 2.15126 | J87: Entire home/apt | L87: 32 | M87: 38 | N87: 45977 | O87: 0.45 | P87: 1 | Q87: 131 | R87: 4 | S87: Spain - National registration number<br />ESFCNT00000805900019883700000000000000000000000000007
A88: 29982718 | B88: 3 bdrooms: King, Queen & single Excellent Location | C88: 34661991 | D88: 1.4655109e+18 | E88: Box Barna | F88: Sants-MontjuÃ¯c | G88: el Poble Sec | H88: 41.374608 | I88: 2.1666098 | J88: Entire home/apt | L88: 31 | M88: 5 | N88: 45779 | O88: 0.25 | P88: 2 | Q88: 231 | R88: 2
A89: 30757752 | B89: Designer Apartment by Eric VÃ¶kel Sagrada Familia | C89: 228209547 | D89: 1.4692156e+18 | E89: Eric | F89: Eixample | G89: la Sagrada FamÃ­lia | H89: 41.410233 | I89: 2.175056 | J89: Entire home/apt | L89: 1 | M89: 763 | N89: 46004 | O89: 9.26 | P89: 3 | Q89: 281 | R89: 80 | S89: Barcelona - Regional registration number<br />HUTB-000790<br /><br />Spain - National registration number<br />ESHFTU00000805800000941900100000000000000000053198206
A90: 30759793 | B90: Nordic-Designed Apartment near Sagrada Familia | C90: 228209547 | D90: 1.4692156e+18 | E90: Eric | F90: Eixample | G90: la Sagrada FamÃ­lia | H90: 41.410233 | I90: 2.175056 | J90: Entire home/apt | L90: 1 | M90: 1143 | N90: 46004 | O90: 13.6 | P90: 3 | Q90: 286 | R90: 206 | S90: Barcelona - Regional registration number<br />HUTB-000801<br /><br />Spain - National registration number<br />ESHFTU00000805800000941900200000000000000000053772504
A91: 30760234 | B91: Bright Penthouse with Terrace near Sagrada Familia | C91: 228209547 | D91: 1.4692156e+18 | E91: Eric | F91: Eixample | G91: la Sagrada FamÃ­lia | H91: 41.410233 | I91: 2.175056 | J91: Entire home/apt | L91: 1 | M91: 330 | N91: 46002 | O91: 3.93 | P91: 3 | Q91: 264 | R91: 35 | S91: Barcelona - Regional registration number<br />HUTB-000805<br /><br />Spain - National registration number<br />ESHFTU00000805800000941901600000000000000000005779202
A92: 34552880 | B92: Exquisite&historic flat with rooftop | C92: 180215498 | D92: 1.4630741e+18 | E92: Jordi | F92: GrÃ cia | G92: la Vila de GrÃ cia | H92: 41.39729 | I92: 2.15642 | J92: Entire home/apt | L92: 4 | M92: 223 | N92: 45959 | O92: 2.78 | P92: 3 | Q92: 161 | R92: 41 | S92: Barcelona - Regional registration number<br />HUTB-004650<br /><br />Spain - National registration number<br />ESHFTU00000806600000670300200000000000000HUTB-0046508
A93: 34561786 | B93: Great 12 bedr Acomodis GroupFlat Las Ramblas 30ppl | C93: 1447144 | D93: 1.4625181e+18 | E93: Jacob | F93: Ciutat Vella | G93: el Barri GÃ²tic | H93: 41.38073 | I93: 2.17687 | J93: Entire home/apt | L93: 2 | M93: 0 | P93: 428 | Q93: 362 | R93: 0 | S93: Spain - National registration number<br />ESFCTU00000811900020755400000000000000000HUTB-0780005
A94: 34564384 | B94: Oasis penthouse in Sant Antoni Market | C94: 16163954 | D94: 1.4629801e+18 | E94: Weflating | F94: Eixample | G94: Sant Antoni | H94: 41.37621 | I94: 2.16332 | J94: Entire home/apt | L94: 1 | M94: 54 | N94: 45460 | O94: 0.93 | P94: 6 | Q94: 101 | R94: 0 | S94: Spain - National registration number<br />ESFCTU00000806900043411800000000000000HUTB-010114-635
A95: 34564909 | B95: Amazing terrace in Sant Antoni Market | C95: 16163954 | D95: 1.4629801e+18 | E95: Weflating | F95: Eixample | G95: Sant Antoni | H95: 41.37607 | I95: 2.1626 | J95: Entire home/apt | L95: 1 | M95: 142 | N95: 45984 | O95: 2.46 | P95: 6 | Q95: 166 | R95: 30 | S95: Spain - National registration number<br />ESFCTU00000806900043405700000000000000HUTB-010110-594
A96: 35739931 | B96: Barcelona - Center - Room Deprived 1 or 2 persons | C96: 268841602 | D96: 1.4694209e+18 | E96: Ivan | F96: Eixample | G96: el Fort Pienc | H96: 41.40129 | I96: 2.18143 | J96: Private room | L96: 2 | M96: 0 | P96: 1 | Q96: 0 | R96: 0
A97: 36488815 | B97: Eco-Friendly Cozy Studio with kitchenette | C97: 49095152 | D97: 1.4657471e+18 | E97: Eco Boutique Hostal Grau | F97: Ciutat Vella | G97: el Raval | H97: 41.38472 | I97: 2.16814 | J97: Hotel room | L97: 1 | M97: 4 | N97: 45854 | O97: 0.05 | P97: 7 | Q97: 258 | R97: 3 | S97: Barcelona - Regional registration number<br />HB-002211
A98: 36488917 | B98: Eco-Friendly Family Studio with kitchenette | C98: 49095152 | D98: 1.4657471e+18 | E98: Eco Boutique Hostal Grau | F98: Ciutat Vella | G98: el Raval | H98: 41.38472 | I98: 2.16814 | J98: Entire home/apt | L98: 1 | M98: 42 | N98: 45889 | O98: 0.93 | P98: 7 | Q98: 266 | R98: 24 | S98: Barcelona - Regional registration number<br />HUTB-002877
A99: 36489150 | B99: Cozy Apartment in Eco-Friendly and green Hotel | C99: 49095152 | D99: 1.4657471e+18 | E99: Eco Boutique Hostal Grau | F99: Ciutat Vella | G99: el Raval | H99: 41.38472 | I99: 2.16814 | J99: Entire home/apt | L99: 1 | M99: 38 | N99: 45851 | O99: 0.9 | P99: 7 | Q99: 257 | R99: 10 | S99: Barcelona - Regional registration number<br />HUTB-002879<br /><br />Spain - National registration number<br />ESFCTUR0D10805600030187800000000000000000HUTB-0028793
A100: 36499025 | B100: Suite Sants | C100: 90985218 | D100: 1.4671004e+18 | E100: Edgar | F100: Sants-MontjuÃ¯c | G100: Hostafrancs | H100: 41.37401 | I100: 2.14117 | J100: Private room | L100: 3 | M100: 8 | N100: 44822 | O100: 0.14 | P100: 1 | Q100: 0 | R100: 0
...

Sheet Stats
A1: Statistic | B1: Minimum Nights | C1: Number of reviews | D1: Availability 365 | E1: Calculated Host Listings Count
A2: Mean | B2: =AVERAGE(Barcelona!L:L) -> 16.592507 | C2: =AVERAGE(Barcelona!R:R) -> 11.200638 | D2: =AVERAGE(Barcelona!Q:Q) -> 209.57215 | E2: =AVERAGE(Barcelona!P:P) -> 68.490235
A3: Median | B3: =MEDIAN(Barcelona!L:L) -> 3 | C3: =MEDIAN(Barcelona!R:R) -> 1 | D3: =MEDIAN(Barcelona!Q:Q) -> 245 | E3: =MEDIAN(Barcelona!P:P) -> 9
A4: Mode | B4: =MODE(Barcelona!L:L) -> 1 | C4: =MODE(Barcelona!R:R) -> 0 | D4: =MODE(Barcelona!Q:Q) -> 0 | E4: =MODE(Barcelona!P:P) -> 1
A5: Std Deviation | B5: =STDEV(Barcelona!L:L) -> 31.589899 | C5: =STDEV(Barcelona!R:R) -> 24.999374 | D5: =STDEV(Barcelona!Q:Q) -> 130.3137 | E5: =STDEV(Barcelona!P:P) -> 129.19512
A6: Variance | B6: =VAR(Barcelona!L:L) -> 997.92169 | C6: =VAR(Barcelona!R:R) -> 624.96871 | D6: =VAR(Barcelona!Q:Q) -> 16981.659 | E6: =VAR(Barcelona!P:P) -> 16691.379
A7: Min | B7: =MIN(Barcelona!L:L) -> 1 | C7: =MIN(Barcelona!R:R) -> 0 | D7: =MIN(Barcelona!Q:Q) -> 0 | E7: =MIN(Barcelona!P:P) -> 1
A8: Max | B8: =MAX(Barcelona!L:L) -> 1124 | C8: =MAX(Barcelona!R:R) -> 938 | D8: =MAX(Barcelona!Q:Q) -> 365 | E8: =MAX(Barcelona!P:P) -> 549
A9: Range | B9: =MAX(Barcelona!L:L)-MIN(Barcelona!L:L) -> 1123 | C9: =MAX(Barcelona!R:R)-MIN(Barcelona!R:R) -> 938 | D9: =MAX(Barcelona!Q:Q)-MIN(Barcelona!Q:Q) -> 365 | E9: =MAX(Barcelona!P:P)-MIN(Barcelona!P:P) -> 548
A10: Skewness | B10: =SKEW(Barcelona!L:L) -> 14.326116 | C10: =SKEW(Barcelona!R:R) -> 10.901382 | D10: =SKEW(Barcelona!Q:Q) -> -0.43426622 | E10: =SKEW(Barcelona!P:P) -> 2.3615706
A11: Kurtosis | B11: =KURT(Barcelona!L:L) -> 339.21108 | C11: =KURT(Barcelona!R:R) -> 277.00696 | D11: =KURT(Barcelona!Q:Q) -> -1.2864864 | E11: =KURT(Barcelona!P:P) -> 4.8759493
